CHANGELOG
MANIFEST.in
README.md
setup.py
generic_heap/__init__.py
generic_heap.egg-info/PKG-INFO
generic_heap.egg-info/SOURCES.txt
generic_heap.egg-info/dependency_links.txt
generic_heap.egg-info/top_level.txt