Metadata-Version: 1.1
Name: generic-heap
Version: 1.0.1
Summary: Heap data structure,Gives a feel like using priority queue in Java and C++.
Home-page: https://github.com/pritamSarkar123/generic_heap.git
Author: Pritam Sarkar (Vanu)
Author-email: pritamsarkar84208220@gmail.com
License: MIT
Keywords: python,Heap
Platform: UNKNOWN
Classifier: Development Status :: 1 - Planning
Classifier: Intended Audience :: Developers
Classifier: Programming Language :: Python :: 3
Classifier: Operating System :: Unix
Classifier: Operating System :: MacOS :: MacOS X
Classifier: Operating System :: Microsoft :: Windows
Classifier: License :: OSI Approved :: MIT License
